MANIFEST.in
README.md
pyproject.toml
setup.py
amuse_tests.egg-info/PKG-INFO
amuse_tests.egg-info/SOURCES.txt
amuse_tests.egg-info/dependency_links.txt
amuse_tests.egg-info/requires.txt
amuse_tests.egg-info/top_level.txt
src/amuse/test/suite/__init__.py
src/amuse/test/suite/_version.py
src/amuse/test/suite/codes_tests/__init__.py
src/amuse/test/suite/codes_tests/gd_tests.py
src/amuse/test/suite/codes_tests/legacy_support.py
src/amuse/test/suite/codes_tests/test_aarsethzare.py
src/amuse/test/suite/codes_tests/test_adaptb.py
src/amuse/test/suite/codes_tests/test_athena.py
src/amuse/test/suite/codes_tests/test_bhtree.py
src/amuse/test/suite/codes_tests/test_bonsai.py
src/amuse/test/suite/codes_tests/test_bonsai2.py
src/amuse/test/suite/codes_tests/test_bridge.py
src/amuse/test/suite/codes_tests/test_brutus.py
src/amuse/test/suite/codes_tests/test_bse.py
src/amuse/test/suite/codes_tests/test_capreole.py
src/amuse/test/suite/codes_tests/test_create_dir.py
src/amuse/test/suite/codes_tests/test_encounters.py
src/amuse/test/suite/codes_tests/test_evtwin.py
src/amuse/test/suite/codes_tests/test_fastkick.py
src/amuse/test/suite/codes_tests/test_fi.py
src/amuse/test/suite/codes_tests/test_gadget2.py
src/amuse/test/suite/codes_tests/test_galactics.py
src/amuse/test/suite/codes_tests/test_galaxia.py
src/amuse/test/suite/codes_tests/test_gravity_codes.py
src/amuse/test/suite/codes_tests/test_hacs64.py
src/amuse/test/suite/codes_tests/test_halogen.py
src/amuse/test/suite/codes_tests/test_hermite.py
src/amuse/test/suite/codes_tests/test_higpus.py
src/amuse/test/suite/codes_tests/test_hop.py
src/amuse/test/suite/codes_tests/test_huayno.py
src/amuse/test/suite/codes_tests/test_interface.py
src/amuse/test/suite/codes_tests/test_kepler.py
src/amuse/test/suite/codes_tests/test_krome.py
src/amuse/test/suite/codes_tests/test_lab.py
src/amuse/test/suite/codes_tests/test_mercury.py
src/amuse/test/suite/codes_tests/test_mesa_15140.py
src/amuse/test/suite/codes_tests/test_mesa_2208.py
src/amuse/test/suite/codes_tests/test_mi6.py
src/amuse/test/suite/codes_tests/test_mikkola.py
src/amuse/test/suite/codes_tests/test_mmams.py
